{
  "medicamentos": [
    {
      "id": 1,
      "titulo": "Paracetamol",
      "descricao": "Medicamento utilizado para alívio de febre e dores leves a moderadas."
    },
    {
      "id": 2,
      "titulo": "Ibuprofeno",
      "descricao": "Anti-inflamatório usado para tratar dor, febre e inflamações."
    },
    {
      "id": 3,
      "titulo": "Amoxicilina",
      "descricao": "Antibiótico utilizado no tratamento de infecções bacterianas."
    },
    {
      "id": 4,
      "titulo": "Dipirona",
      "descricao": "Analgésico e antipirético usado para tratar dores e febre."
    },
    {
      "id": 5,
      "titulo": "Omeprazol",
      "descricao": "Medicamento utilizado para tratar problemas gástricos, como refluxo e úlceras."
    },
    {
      "id": 6,
      "titulo": "Losartana",
      "descricao": "Antihipertensivo usado no controle da pressão arterial."
    },
    {
      "id": 7,
      "titulo": "Aspirina",
      "descricao": "Analgésico e anti-inflamatório usado para dores e prevenção de tromboses."
    },
    {
      "id": 8,
      "titulo": "Cetirizina",
      "descricao": "Antialérgico utilizado para tratar sintomas de alergias."
    },
    {
      "id": 9,
      "titulo": "Loratadina",
      "descricao": "Antialérgico usado para tratar alergias respiratórias e de pele."
    },
    {
      "id": 10,
      "titulo": "Simeticona",
      "descricao": "Medicamento usado para aliviar gases intestinais."
    },
    {
      "id": 11,
      "titulo": "Paracetamol",
      "descricao": "Medicamento utilizado para alívio de febre e dores leves a moderadas."
    },
    {
      "id": 12,
      "titulo": "Ibuprofeno",
      "descricao": "Anti-inflamatório usado para tratar dor, febre e inflamações."
    },
    {
      "id": 13,
      "titulo": "Amoxicilina",
      "descricao": "Antibiótico utilizado no tratamento de infecções bacterianas."
    },
    {
      "id": 14,
      "titulo": "Dipirona",
      "descricao": "Analgésico e antipirético usado para tratar dores e febre."
    },
    {
      "id": 15,
      "titulo": "Omeprazol",
      "descricao": "Medicamento utilizado para tratar problemas gástricos, como refluxo e úlceras."
    },
    {
      "id": 16,
      "titulo": "Losartana",
      "descricao": "Antihipertensivo usado no controle da pressão arterial."
    },
    {
      "id": 17,
      "titulo": "Aspirina",
      "descricao": "Analgésico e anti-inflamatório usado para dores e prevenção de tromboses."
    },
    {
      "id": 18,
      "titulo": "Cetirizina",
      "descricao": "Antialérgico utilizado para tratar sintomas de alergias."
    },
    {
      "id": 19,
      "titulo": "Loratadina",
      "descricao": "Antialérgico usado para tratar alergias respiratórias e de pele."
    },
    {
      "id": 20,
      "titulo": "Simeticona",
      "descricao": "Medicamento usado para aliviar gases intestinais."
    },
    {
      "id": 21,
      "titulo": "Paracetamol",
      "descricao": "Medicamento utilizado para alívio de febre e dores leves a moderadas."
    },
    {
      "id": 22,
      "titulo": "Ibuprofeno",
      "descricao": "Anti-inflamatório usado para tratar dor, febre e inflamações."
    },
    {
      "id": 23,
      "titulo": "Amoxicilina",
      "descricao": "Antibiótico utilizado no tratamento de infecções bacterianas."
    },
    {
      "id": 24,
      "titulo": "Dipirona",
      "descricao": "Analgésico e antipirético usado para tratar dores e febre."
    },
    {
      "id": 25,
      "titulo": "Omeprazol",
      "descricao": "Medicamento utilizado para tratar problemas gástricos, como refluxo e úlceras."
    },
    {
      "id": 26,
      "titulo": "Losartana",
      "descricao": "Antihipertensivo usado no controle da pressão arterial."
    },
    {
      "id": 27,
      "titulo": "Aspirina",
      "descricao": "Analgésico e anti-inflamatório usado para dores e prevenção de tromboses."
    },
    {
      "id": 28,
      "titulo": "Cetirizina",
      "descricao": "Antialérgico utilizado para tratar sintomas de alergias."
    },
    {
      "id": 29,
      "titulo": "Loratadina",
      "descricao": "Antialérgico usado para tratar alergias respiratórias e de pele."
    },
    {
      "id": 30,
      "titulo": "Simeticona",
      "descricao": "Medicamento usado para aliviar gases intestinais."
    },
    {
      "id": 31,
      "titulo": "Paracetamol",
      "descricao": "Medicamento utilizado para alívio de febre e dores leves a moderadas."
    },
    {
      "id": 32,
      "titulo": "Ibuprofeno",
      "descricao": "Anti-inflamatório usado para tratar dor, febre e inflamações."
    },
    {
      "id": 33,
      "titulo": "Amoxicilina",
      "descricao": "Antibiótico utilizado no tratamento de infecções bacterianas."
    },
    {
      "id": 34,
      "titulo": "Dipirona",
      "descricao": "Analgésico e antipirético usado para tratar dores e febre."
    },
    {
      "id": 35,
      "titulo": "Omeprazol",
      "descricao": "Medicamento utilizado para tratar problemas gástricos, como refluxo e úlceras."
    },
    {
      "id": 36,
      "titulo": "Losartana",
      "descricao": "Antihipertensivo usado no controle da pressão arterial."
    },
    {
      "id": 37,
      "titulo": "Aspirina",
      "descricao": "Analgésico e anti-inflamatório usado para dores e prevenção de tromboses."
    },
    {
      "id": 38,
      "titulo": "Cetirizina",
      "descricao": "Antialérgico utilizado para tratar sintomas de alergias."
    },
    {
      "id": 39,
      "titulo": "Loratadina",
      "descricao": "Antialérgico usado para tratar alergias respiratórias e de pele."
    },
    {
      "id": 40,
      "titulo": "Simeticona",
      "descricao": "Medicamento usado para aliviar gases intestinais."
    },
    {
      "id": 41,
      "titulo": "Paracetamol",
      "descricao": "Medicamento utilizado para alívio de febre e dores leves a moderadas."
    },
    {
      "id": 42,
      "titulo": "Ibuprofeno",
      "descricao": "Anti-inflamatório usado para tratar dor, febre e inflamações."
    },
    {
      "id": 43,
      "titulo": "Amoxicilina",
      "descricao": "Antibiótico utilizado no tratamento de infecções bacterianas."
    },
    {
      "id": 44,
      "titulo": "Dipirona",
      "descricao": "Analgésico e antipirético usado para tratar dores e febre."
    },
    {
      "id": 45,
      "titulo": "Omeprazol",
      "descricao": "Medicamento utilizado para tratar problemas gástricos, como refluxo e úlceras."
    },
    {
      "id": 46,
      "titulo": "Losartana",
      "descricao": "Antihipertensivo usado no controle da pressão arterial."
    },
    {
      "id": 47,
      "titulo": "Aspirina",
      "descricao": "Analgésico e anti-inflamatório usado para dores e prevenção de tromboses."
    },
    {
      "id": 48,
      "titulo": "Cetirizina",
      "descricao": "Antialérgico utilizado para tratar sintomas de alergias."
    },
    {
      "id": 49,
      "titulo": "Loratadina",
      "descricao": "Antialérgico usado para tratar alergias respiratórias e de pele."
    },
    {
      "id": 50,
      "titulo": "Simeticona",
      "descricao": "Medicamento usado para aliviar gases intestinais."
    },
    {
      "id": 51,
      "titulo": "Paracetamol",
      "descricao": "Medicamento utilizado para alívio de febre e dores leves a moderadas."
    },
    {
      "id": 52,
      "titulo": "Ibuprofeno",
      "descricao": "Anti-inflamatório usado para tratar dor, febre e inflamações."
    },
    {
      "id": 53,
      "titulo": "Amoxicilina",
      "descricao": "Antibiótico utilizado no tratamento de infecções bacterianas."
    },
    {
      "id": 54,
      "titulo": "Dipirona",
      "descricao": "Analgésico e antipirético usado para tratar dores e febre."
    },
    {
      "id": 55,
      "titulo": "Omeprazol",
      "descricao": "Medicamento utilizado para tratar problemas gástricos, como refluxo e úlceras."
    },
    {
      "id": 56,
      "titulo": "Losartana",
      "descricao": "Antihipertensivo usado no controle da pressão arterial."
    },
    {
      "id": 57,
      "titulo": "Aspirina",
      "descricao": "Analgésico e anti-inflamatório usado para dores e prevenção de tromboses."
    },
    {
      "id": 58,
      "titulo": "Cetirizina",
      "descricao": "Antialérgico utilizado para tratar sintomas de alergias."
    },
    {
      "id": 59,
      "titulo": "Loratadina",
      "descricao": "Antialérgico usado para tratar alergias respiratórias e de pele."
    },
    {
      "id": 60,
      "titulo": "Simeticona",
      "descricao": "Medicamento usado para aliviar gases intestinais."
    },
    {
      "id": 61,
      "titulo": "Paracetamol",
      "descricao": "Medicamento utilizado para alívio de febre e dores leves a moderadas."
    },
    {
      "id": 62,
      "titulo": "Ibuprofeno",
      "descricao": "Anti-inflamatório usado para tratar dor, febre e inflamações."
    },
    {
      "id": 63,
      "titulo": "Amoxicilina",
      "descricao": "Antibiótico utilizado no tratamento de infecções bacterianas."
    },
    {
      "id": 64,
      "titulo": "Dipirona",
      "descricao": "Analgésico e antipirético usado para tratar dores e febre."
    },
    {
      "id": 65,
      "titulo": "Omeprazol",
      "descricao": "Medicamento utilizado para tratar problemas gástricos, como refluxo e úlceras."
    },
    {
      "id": 66,
      "titulo": "Losartana",
      "descricao": "Antihipertensivo usado no controle da pressão arterial."
    },
    {
      "id": 67,
      "titulo": "Aspirina",
      "descricao": "Analgésico e anti-inflamatório usado para dores e prevenção de tromboses."
    },
    {
      "id": 68,
      "titulo": "Cetirizina",
      "descricao": "Antialérgico utilizado para tratar sintomas de alergias."
    },
    {
      "id": 69,
      "titulo": "Loratadina",
      "descricao": "Antialérgico usado para tratar alergias respiratórias e de pele."
    },
    {
      "id": 70,
      "titulo": "Simeticona",
      "descricao": "Medicamento usado para aliviar gases intestinais."
    },
    {
      "id": 71,
      "titulo": "Paracetamol",
      "descricao": "Medicamento utilizado para alívio de febre e dores leves a moderadas."
    },
    {
      "id": 72,
      "titulo": "Ibuprofeno",
      "descricao": "Anti-inflamatório usado para tratar dor, febre e inflamações."
    },
    {
      "id": 73,
      "titulo": "Amoxicilina",
      "descricao": "Antibiótico utilizado no tratamento de infecções bacterianas."
    },
    {
      "id": 74,
      "titulo": "Dipirona",
      "descricao": "Analgésico e antipirético usado para tratar dores e febre."
    },
    {
      "id": 75,
      "titulo": "Omeprazol",
      "descricao": "Medicamento utilizado para tratar problemas gástricos, como refluxo e úlceras."
    },
    {
      "id": 76,
      "titulo": "Losartana",
      "descricao": "Antihipertensivo usado no controle da pressão arterial."
    },
    {
      "id": 77,
      "titulo": "Aspirina",
      "descricao": "Analgésico e anti-inflamatório usado para dores e prevenção de tromboses."
    },
    {
      "id": 78,
      "titulo": "Cetirizina",
      "descricao": "Antialérgico utilizado para tratar sintomas de alergias."
    },
    {
      "id": 79,
      "titulo": "Loratadina",
      "descricao": "Antialérgico usado para tratar alergias respiratórias e de pele."
    },
    {
      "id": 80,
      "titulo": "Simeticona",
      "descricao": "Medicamento usado para aliviar gases intestinais."
    },
    {
      "id": 81,
      "titulo": "Paracetamol",
      "descricao": "Medicamento utilizado para alívio de febre e dores leves a moderadas."
    },
    {
      "id": 82,
      "titulo": "Ibuprofeno",
      "descricao": "Anti-inflamatório usado para tratar dor, febre e inflamações."
    },
    {
      "id": 83,
      "titulo": "Amoxicilina",
      "descricao": "Antibiótico utilizado no tratamento de infecções bacterianas."
    },
    {
      "id": 84,
      "titulo": "Dipirona",
      "descricao": "Analgésico e antipirético usado para tratar dores e febre."
    },
    {
      "id": 85,
      "titulo": "Omeprazol",
      "descricao": "Medicamento utilizado para tratar problemas gástricos, como refluxo e úlceras."
    },
    {
      "id": 86,
      "titulo": "Losartana",
      "descricao": "Antihipertensivo usado no controle da pressão arterial."
    },
    {
      "id": 87,
      "titulo": "Aspirina",
      "descricao": "Analgésico e anti-inflamatório usado para dores e prevenção de tromboses."
    },
    {
      "id": 88,
      "titulo": "Cetirizina",
      "descricao": "Antialérgico utilizado para tratar sintomas de alergias."
    },
    {
      "id": 89,
      "titulo": "Loratadina",
      "descricao": "Antialérgico usado para tratar alergias respiratórias e de pele."
    },
    {
      "id": 90,
      "titulo": "Simeticona",
      "descricao": "Medicamento usado para aliviar gases intestinais."
    },
    {
      "id": 91,
      "titulo": "Paracetamol",
      "descricao": "Medicamento utilizado para alívio de febre e dores leves a moderadas."
    },
    {
      "id": 92,
      "titulo": "Ibuprofeno",
      "descricao": "Anti-inflamatório usado para tratar dor, febre e inflamações."
    },
    {
      "id": 93,
      "titulo": "Amoxicilina",
      "descricao": "Antibiótico utilizado no tratamento de infecções bacterianas."
    },
    {
      "id": 94,
      "titulo": "Dipirona",
      "descricao": "Analgésico e antipirético usado para tratar dores e febre."
    },
    {
      "id": 95,
      "titulo": "Omeprazol",
      "descricao": "Medicamento utilizado para tratar problemas gástricos, como refluxo e úlceras."
    },
    {
      "id": 96,
      "titulo": "Losartana",
      "descricao": "Antihipertensivo usado no controle da pressão arterial."
    },
    {
      "id": 97,
      "titulo": "Aspirina",
      "descricao": "Analgésico e anti-inflamatório usado para dores e prevenção de tromboses."
    },
    {
      "id": 98,
      "titulo": "Cetirizina",
      "descricao": "Antialérgico utilizado para tratar sintomas de alergias."
    },
    {
      "id": 99,
      "titulo": "Loratadina",
      "descricao": "Antialérgico usado para tratar alergias respiratórias e de pele."
    },
    {
      "id": 100,
      "titulo": "Simeticona",
      "descricao": "Medicamento usado para aliviar gases intestinais."
    }
  ]
}
